beetsplug/__init__.py
beetsplug/abcalc.py
beetsplug/advisory.py
beetsplug/alias.py
beetsplug/alternativesplaylist.py
beetsplug/convertsingletons.py
beetsplug/crossquery.py
beetsplug/existingqueries.py
beetsplug/hasart.py
beetsplug/importinspect.py
beetsplug/inconsistentalbumtracks.py
beetsplug/inlinehook.py
beetsplug/last_import.py
beetsplug/modifyonimport.py
beetsplug/modifytmpl.py
beetsplug/musicsource.py
beetsplug/nowrite.py
beetsplug/otherqueries.py
beetsplug/picard.py
beetsplug/reimportskipfields.py
beetsplug/replaceformat.py
beetsplug/savedformats.py
beetsplug/savedqueries.py
beetsplug/sorted_model_changes.py
beetsplug/spotifyexplicit.py
beetsplug/zeroalbum.py
beets_kergoth-0.4.0.dist-info/LICENSE.md
beets_kergoth-0.4.0.dist-info/WHEEL
beets_kergoth-0.4.0.dist-info/METADATA
beets_kergoth-0.4.0.dist-info/RECORD
