Metadata-Version: 2.1
Name: beets-kergoth
Version: 0.4.0
Summary: Various personal beets plugins that don't yet have a home elsewhere.
Home-page: https://github.com/kergoth/beets-kergoth
Author: Christopher Larson
Author-email: kergoth@gmail.com
Requires-Python: >=2.7, !=3.0.*, !=3.1.*, !=3.2.*, !=3.3.*, !=3.8.*
Classifier: Development Status :: 4 - Beta
Classifier: Environment :: Plugins
Classifier: Programming Language :: Python :: 2
Classifier: Programming Language :: Python :: 2.7
Classifier: Programming Language :: Python :: 3
Classifier: Programming Language :: Python :: 3.4
Classifier: Programming Language :: Python :: 3.5
Classifier: Programming Language :: Python :: 3.6
Classifier: Programming Language :: Python :: 3.7
Classifier: Topic :: Multimedia :: Sound/Audio
Requires-Dist: beets (>=1.4,<2.0)
Requires-Dist: confuse (>=1.0.0,<2.0.0)
Requires-Dist: mediafile (>=0.2.0,<0.3.0)
Project-URL: Repository, https://github.com/kergoth/beets-kergoth
